dev_utils/__init__.py
dev_utils/downloader.py
dev_utils/email_utils.py
dev_utils/log.py
dev_utils/mongo_bulk.py
dev_utils/proxy_utils.py
dev_utils/uas.py
dev_utils-4.0.2.dist-info/LICENSE
dev_utils-4.0.2.dist-info/METADATA
dev_utils-4.0.2.dist-info/WHEEL
dev_utils-4.0.2.dist-info/top_level.txt
dev_utils-4.0.2.dist-info/RECORD
