Metadata-Version: 2.1
Name: dev-utils
Version: 4.0.2
Summary: utils
Home-page: https://github.com/pypa/sampleproject
Author: p
Author-email: author@example.com
License: UNKNOWN
Platform: UNKNOWN
Classifier: Programming Language :: Python :: 3
Classifier: License :: OSI Approved :: MIT License
Classifier: Operating System :: OS Independent
Requires-Python: >=3.5
License-File: LICENSE
